clpy/__init__.py
clpy-0.0.0a0.dist-info/METADATA
clpy-0.0.0a0.dist-info/RECORD
clpy-0.0.0a0.dist-info/WHEEL
clpy-0.0.0a0.dist-info/top_level.txt
