Metadata-Version: 2.1
Name: clpy
Version: 0.0.0a0
Summary: ClPy: OpenCL backend for CuPy
Home-page: https://github.com/fixstars/clpy
Author: Fixstars Corporation
Author-email: clpy@fixstars.com
License: MIT License
Platform: UNKNOWN
